health_cpath/configs/run_ids.py
health_cpath/configs/classification/BaseMIL.py
health_cpath/configs/classification/DeepSMILECrck.py
health_cpath/configs/classification/DeepSMILEPanda.py
health_cpath/configs/classification/DeepSMILESlidesPandaBenchmark.py
health_cpath/datamodules/base_module.py
health_cpath/datamodules/panda_module.py
health_cpath/datamodules/panda_module_benchmark.py
health_cpath/datamodules/tcga_crck_module.py
health_cpath/datasets/base_dataset.py
health_cpath/datasets/dataset_return_index.py
health_cpath/datasets/default_paths.py
health_cpath/datasets/panda_dataset.py
health_cpath/datasets/panda_tiles_dataset.py
health_cpath/datasets/tcga_crck_tiles_dataset.py
health_cpath/datasets/tcga_prad_dataset.py
health_cpath/models/deepmil.py
health_cpath/models/encoders.py
health_cpath/models/transforms.py
health_cpath/preprocessing/create_panda_tiles_dataset.py
health_cpath/preprocessing/create_tiles_dataset.py
health_cpath/preprocessing/loading.py
health_cpath/preprocessing/tiff_conversion.py
health_cpath/preprocessing/tiling.py
health_cpath/scripts/aggregate_metrics_crossvalidation.py
health_cpath/scripts/create_montage.py
health_cpath/scripts/generate_checkpoint_url.py
health_cpath/scripts/generate_crossval_report.py
health_cpath/scripts/mount_azure_dataset.py
health_cpath/scripts/tcga_dataset_prep.py
health_cpath/utils/__init__.py
health_cpath/utils/analysis_plot_utils.py
health_cpath/utils/callbacks.py
health_cpath/utils/deepmil_utils.py
health_cpath/utils/download_utils.py
health_cpath/utils/girder.py
health_cpath/utils/heatmap_utils.py
health_cpath/utils/layer_utils.py
health_cpath/utils/montage.py
health_cpath/utils/montage_config.py
health_cpath/utils/naming.py
health_cpath/utils/output_utils.py
health_cpath/utils/package_setup.py
health_cpath/utils/plots_utils.py
health_cpath/utils/report_utils.py
health_cpath/utils/tcga_utils.py
health_cpath/utils/tiff_conversion_config.py
health_cpath/utils/tiles_selection_utils.py
hi_ml_cpath-0.5.2.dist-info/METADATA
hi_ml_cpath-0.5.2.dist-info/WHEEL
hi_ml_cpath-0.5.2.dist-info/top_level.txt
hi_ml_cpath-0.5.2.dist-info/RECORD
