Metadata-Version: 2.1
Name: hi-ml-cpath
Version: 0.5.2
Summary: Microsoft Health Futures package for deep learning on histopathology images
Home-page: https://github.com/microsoft/hi-ml
Author: Biomedical Imaging Team @ Microsoft Health Futures
Author-email: innereyedev@microsoft.com
License: MIT License
Keywords: Health Futures,Health Intelligence,Computational Pathology,AzureML
Platform: UNKNOWN
Classifier: Development Status :: 3 - Alpha
Classifier: Intended Audience :: Science/Research
Classifier: Topic :: Scientific/Engineering :: Medical Science Apps.
Classifier: License :: OSI Approved :: MIT License
Classifier: Programming Language :: Python :: 3.9
Requires-Dist: coloredlogs (==15.0.1)
Requires-Dist: cucim (==22.10.00)
Requires-Dist: girder-client (==3.1.14)
Requires-Dist: hi-ml
Requires-Dist: ipykernel (==6.21.2)
Requires-Dist: lightning-bolts (==0.4.0)
Requires-Dist: monai-weekly (==1.2.dev2310)
Requires-Dist: more-itertools (==8.10.0)
Requires-Dist: numpy (==1.22.0)
Requires-Dist: pillow (==10.0.1)
Requires-Dist: pydicom (==2.3.0)
Requires-Dist: scikit-image (==0.19.3)
Requires-Dist: scipy (==1.10.0)
Requires-Dist: seaborn (==0.13.0)
Requires-Dist: simpleitk (==2.1.1.2)
Requires-Dist: tifffile (==2022.10.10)
Requires-Dist: timm (==0.6.12)
Requires-Dist: torch (==1.11)
Requires-Dist: torchmetrics (==0.10.2)
Requires-Dist: torchstain (==1.3.0)
Requires-Dist: umap-learn (==0.5.2)
Requires-Dist: yacs (==0.1.8)
